xml_node.py
xml_objects-0.1.1.dist-info/METADATA
xml_objects-0.1.1.dist-info/RECORD
xml_objects-0.1.1.dist-info/WHEEL
xml_objects-0.1.1.dist-info/top_level.txt
