Metadata-Version: 2.1
Name: xml-objects
Version: 0.1.1
Summary: Allows investigation and manipulation of XML data with objects.
Home-page: https://github.com/rpalo/xml-objects
Author: Ryan Palo
Author-email: ryan@thepalos.com
License: UNKNOWN
Project-URL: Author Website, https://assertnotmagic.com
